code2markdown/Code.py
code2markdown/__init__.py
code2markdown/__main__.py
code2markdown/file-types.toml
code2markdown-0.1.dist-info/entry_points.txt
code2markdown-0.1.dist-info/LICENSE
code2markdown-0.1.dist-info/WHEEL
code2markdown-0.1.dist-info/METADATA
code2markdown-0.1.dist-info/RECORD
