Metadata-Version: 2.1
Name: code2markdown
Version: 0.1
Summary: A simple converter for code to markdown.
Home-page: https://github.com/GEM7318/Code2Markdown
License: UNKNOWN
Author: Grant Murray
Author-email: gmurray203@gmail.com
Classifier: License :: OSI Approved :: MIT License
